flask_cookies_cccnrc/__init__.py
flask_cookies_cccnrc/static/bootstrap.bundle.min.js
flask_cookies_cccnrc/static/bootstrap.min.css
flask_cookies_cccnrc/static/cookies-logo.png
flask_cookies_cccnrc/static/cookies.css
flask_cookies_cccnrc/templates/cookies/cookies.html
flask_cookies_cccnrc-0.0.1.dist-info/METADATA
flask_cookies_cccnrc-0.0.1.dist-info/WHEEL
flask_cookies_cccnrc-0.0.1.dist-info/licenses/LICENSE
flask_cookies_cccnrc-0.0.1.dist-info/RECORD
